pyuni10/__init__.py
pyuni10/libuni10.2.1.2.dylib
pyuni10/libuni10.2.dylib
pyuni10/libuni10.dylib
pyuni10/pyuni10.cpython-37m-darwin.so
pyuni10-2.1.2.dist-info/LICENSE
pyuni10-2.1.2.dist-info/METADATA
pyuni10-2.1.2.dist-info/WHEEL
pyuni10-2.1.2.dist-info/top_level.txt
pyuni10-2.1.2.dist-info/RECORD
